README.rst
setup.py
foo/__init__.py
stickynotes_client.egg-info/PKG-INFO
stickynotes_client.egg-info/SOURCES.txt
stickynotes_client.egg-info/dependency_links.txt
stickynotes_client.egg-info/not-zip-safe
stickynotes_client.egg-info/top_level.txt